{
  "meta": {
    "title": "§ 2. რაციონალური რიცხვები – სავარჯიშოები",
    "navLabel": "ნაწილი II"
  },
  "sections": [
    {
      "title": "2.1. შეადარეთ წილადები:",
      "blocks": [
        {
          "type": "ordered-list",
          "items": [
            {
              "number": "1)",
              "text": "\\( \\frac{4}{11} \\) და \\( \\frac{6}{11} \\);"
            },
            {
              "number": "2)",
              "text": "\\( \\frac{7}{11} \\) და \\( \\frac{1}{4} \\);"
            },
            {
              "number": "3)",
              "text": "\\( \\frac{15}{19} \\) და \\( \\frac{19}{19} \\);"
            },
            {
              "number": "4)",
              "text": "\\( \\frac{3}{5} \\) და \\( \\frac{6}{8} \\);"
            },
            {
              "number": "5)",
              "text": "\\( \\frac{11}{12} \\) და \\( \\frac{8}{8} \\);"
            },
            {
              "number": "6)",
              "text": "\\( \\frac{2}{160} \\) და \\( \\frac{31 - 2}{240} \\);"
            },
            {
              "number": "7)",
              "text": "\\( \\frac{20}{35} \\) და \\( \\frac{5}{721} \\);"
            },
            {
              "number": "8)",
              "text": "\\( \\frac{9}{8} \\)."
            }
          ]
        }
      ]
    },
    {
      "title": "2.2. შემდეგი რიცხვები დაალაგეთ ზრდადობის მიხედვით და მიუთითეთ მათ შორის ტოლები:",
      "blocks": [
        {
          "type": "paragraph",
          "text": "\\( \\frac {1}{24}, \\frac {11}{24}, \\frac {12}{24}, \\frac {15}{24}, \\frac {16}{24}, \\frac {22}{24}, \\frac {3}{12}, \\frac {5}{12}, \\frac {3}{6}, \\frac {1}{4}, \\frac {2}{3}, \\frac {1}{2} \\)"
        }
      ]
    },
    {
      "title": "2.3. განსაზღვრეთ რომელი წილადია ერთთან უფრო ახლოს და შეადარეთ ისინი:",
      "blocks": [
        {
          "type": "paragraph",
          "text": "\\( \\frac {4}{3}, \\frac {3}{5}, \\frac {7}{8}, \\frac {6}{9}, \\frac {99}{100}, \\frac {1010}{51231}, \\frac {4}{5} \\)"
        }
      ]
    },
    {
      "title": "2.4.",
      "blocks": [
        {
          "type": "paragraph",
          "text": "2 კგ შოკოლადი თანაბრად გაანაწილეს 10 პაკეტში, 5 კგ ნამცხვარი კი 15 პაკეტში. რომელი პაკეტია უფრო მძიმე?"
        }
      ]
    },
    {
      "title": "2.5.",
      "blocks": [
        {
          "type": "paragraph",
          "text": "ერთმა ტურისტმა 21 კმ გაიარა 2 სთ-ში, მეორემ კი 28 კმ 3 სთ-ში. რომელი ტურისტია უფრო სწრაფი?"
        }
      ]
    },
    {
      "title": "2.6.",
      "blocks": [
        {
          "type": "paragraph",
          "text": "გია, დათო და ბექა ღობეს ღებავდნენ. გიამ მთელი სამუშაოს \\( \\frac {3}{10} \\) ნაწილი შეასრულა, დათომ \\( \\frac {5}{8} \\), ბექამ კი – \\( \\frac {3}{40} \\). რომელმა შეასრულა სამუშაოს მეტი ნაწილი?"
        }
      ]
    },
    {
      "title": "2.7.",
      "blocks": [
        {
          "type": "paragraph",
          "text": "გოგი 8 წამში 5 ნაბიჯს დგამს, ლევანი კი 5 წამში იმავე სიგრძის 3 ნაბიჯს. რომელი უფრო სწრაფად დადის?"
        }
      ]
    },
    {
      "title": "2.8. მოცემული წილადი ჩაწერეთ არაწესიერი წილადის სახით:",
      "blocks": [
        {
          "type": "paragraph",
          "text": "\\( \\frac {1}{2}, \\frac {3}{4}, \\frac {3}{5}, \\frac {9}{7}, \\frac {2}{1}, \\frac {3}{2}, \\frac {4}{3}, -\\frac {2}{4}, \\frac {5}{15}, \\frac {6}{20}, \\frac {1}{3} \\)."
        }
      ]
    },
    {
      "title": "2.9. მოცემული წილადი ჩაწერეთ შერეული წილადის სახით:",
      "blocks": [
        {
          "type": "paragraph",
          "text": "\\( \\frac {11}{8}, \\frac {12}{5} \\) და სხვ."
        }
      ]
    },
    {
      "title": "2.10. შეასრულეთ მოქმედებები",
      "blocks": [
        {
          "type": "paragraph",
          "text": "\\( \\frac {57}{8} + \\frac {12}{61}; \\frac {15}{4} - \\frac {20}{11}; 3 + \\frac {-5}{3}; 5 - \\frac {3}{41}; \\frac {100}{6} + \\frac {3}{4} + 3; \\frac {251}{6} + 3 + 18 + \\frac {27}{30}; 7 - 20; 10 - 80 - 5;\\)"
        }
      ]
    },
    {
      "title": "2.11. შეასრულეთ მოქმედებები",
      "blocks": [
        {
          "type": "paragraph",
          "text": "1) \\( \\frac {4}{12}; \\)"
        },
        {
          "type": "paragraph",
          "text": "2) \\( 3 - 32.5; \\)"
        },
        {
          "type": "paragraph",
          "text": "3) \\( 34 - 2:2; \\)"
        },
        {
          "type": "paragraph",
          "text": "4) \\( \\frac {43}{35}; \\)"
        },
        {
          "type": "paragraph",
          "text": "5) \\( 10 - 2; \\)"
        },
        {
          "type": "paragraph",
          "text": "6) \\( 3 - 9; \\)"
        },
        {
          "type": "paragraph",
          "text": "7) \\( 18 : 2; \\)"
        },
        {
          "type": "paragraph",
          "text": "8) \\( 7 : 11. \\)"
        }
      ]
    },
    {
      "title": "2.12.",
      "blocks": [
        {
          "type": "paragraph",
          "text": "\\( 1) 5,5+6,5; 2) 5,5+(-6,5); 3) -5,5+6,5; 4) -5,5+(-6,5); 5) 5,5-6,5; 6) 5,5-(-6,5); 7) -5,5-6,5; 8) -5,5-(-6,5). \\)"
        }
      ]
    },
    {
      "title": "2.13.",
      "blocks": [
        {
          "type": "paragraph",
          "text": "\\( 1) 2,4-3; 2) -2,4-3; 3) (-2,4)-(-3); 4) 2,4-(-3); 5) 2,4:3; 6) -2,4:3; 7) 2,4:(-3); 8) -2,4:(-3). \\)"
        }
      ]
    },
    {
      "title": "2.14.",
      "blocks": [
        {
          "type": "paragraph",
          "text": "1) სპორტსმენი 2 მ სიმაღლეზე გადახტა, რაც \\(1\\frac {3}{7}\\) ჯერ მეტია მის სიმაღლეზე. იპოვეთ სპორტსმენის სიმაღლე."
        },
        {
          "type": "paragraph",
          "text": "2) დილის 9 საათზე ბოძის ჩრდილის სიგრძე \\(4\\frac {1}{2}\\) მ-ის ტოლია, რაც \\(1\\frac {1}{8}\\)-ჯერ ნაკლებია ბოძის სიმაღლეზე. იპოვეთ ბოძის სიმაღლე."
        }
      ]
    },
    {
      "title": "2.15.",
      "blocks": [
        {
          "type": "paragraph",
          "text": "1) \\((11,81+8,19)-0,02\\);"
        },
        {
          "type": "paragraph",
          "text": "2) \\(9-0,08+0,7-0,9;\\)"
        },
        {
          "type": "paragraph",
          "text": "3) \\((1,11+5,19):0,21;\\)"
        },
        {
          "type": "paragraph",
          "text": "4) \\((5,25-1,5):2,5.\\)"
        }
      ]
    },
    {
      "title": "2.16.",
      "blocks": [
        {
          "type": "paragraph",
          "text": "1) \\((7+2):3;\\)"
        },
        {
          "type": "paragraph",
          "text": "2) \\((5+2)\\times 40;\\)"
        },
        {
          "type": "paragraph",
          "text": "3) \\((5+2):100;\\)"
        },
        {
          "type": "paragraph",
          "text": "4) \\((-1+1-63-96;\\)"
        },
        {
          "type": "paragraph",
          "text": "5) \\((-1+3,45);\\)"
        },
        {
          "type": "paragraph",
          "text": "6) \\(9 + \\frac {5}{84};\\)"
        },
        {
          "type": "paragraph",
          "text": "7) \\((3+2)-0,7;\\)"
        },
        {
          "type": "paragraph",
          "text": "8) \\((-2-3-1)-0,4;\\)"
        },
        {
          "type": "paragraph",
          "text": "9) \\( (4+3)-0,24;\\)"
        },
        {
          "type": "paragraph",
          "text": "10) \\((-2+1)-4,48;\\)"
        },
        {
          "type": "paragraph",
          "text": "11) \\((-4+6)-3,84.\\)"
        }
      ]
    },
    {
      "title": "2.17.",
      "blocks": [
        {
          "type": "paragraph",
          "text": "სალომემ იყიდა 4,5 კგ ფორთოხალი და 1 კგ 2\\(\\frac {2}{5}\\). რომელ ხილში გადაიხადა სალომემ მეტი და რამდენით?"
        }
      ]
    },
    {
      "title": "2.18.",
      "blocks": [
        {
          "type": "paragraph",
          "text": "\\( 1) \\frac {14}{5} : 2; 2) 35 : 1 - 7; 3) 39 : 20 + 4; 4) 4,4 : 1; 5) 2,8 : 7; 6) 10 : 3; 7) 65,5 : 22 - 12; 8) 32. \\)"
        }
      ]
    },
    {
      "title": "2.19.",
      "blocks": [
        {
          "type": "paragraph",
          "text": "\\( 1) \\frac {4}{6} - \\frac {2}{12} : (+2); 2) 36 : (4+3); 3) 42 : (7-3); 4) 2,2 : 2 - 3; 5) \\frac {55}{4} : 15; 6) 8,8 : 30 - 10 : 35 : (+4); 7) 32. \\)"
        }
      ]
    },
    {
      "title": "2.20.",
      "blocks": [
        {
          "type": "paragraph",
          "text": "ჩაწერეთ რიცხვითი გამოსახულების სახით და გამოთვალეთ:"
        },
        {
          "type": "paragraph",
          "text": "1) 2,5 და 1,6 რიცხვების ნამრავლისა და \\(3\\frac {1}{3}\\)-ის ჯამი;"
        },
        {
          "type": "paragraph",
          "text": "2) \\( \\frac {1}{2} \\) და \\(2\\frac {3}{5}\\) რიცხვების ნამრავლისა და 2,4-ის სხვაობა;"
        },
        {
          "type": "paragraph",
          "text": "3) 4–1 და 2 რიცხვების სხვაობისა და 5-ის ნამრავლი;"
        },
        {
          "type": "paragraph",
          "text": "4) 4,8 და 2,3 რიცხვების სხვაობისა და \\(13\\frac {1}{4}\\)-ის ნამრავლი."
        }
      ]
    },
    {
      "title": "2.21. შეასრულეთ მოქმედებები",
      "blocks": [
        {
          "type": "ordered-list",
          "items": [
            {
              "number": "1)",
              "text": "(8−13)+7;"
            },
            {
              "number": "2)",
              "text": "\\(\\frac{20}{4} \\quad \\frac{40}{3}\\)"
            },
            {
              "number": "3)",
              "text": "(3+3):($41$);"
            },
            {
              "number": "4)",
              "text": "\\(\\frac{3}{7} \\quad \\frac{7}{3}\\)"
            },
            {
              "number": "5)",
              "text": "(13−2):1;"
            },
            {
              "number": "6)",
              "text": "\\(\\frac{4}{6} \\quad \\frac{8}{9}\\)"
            },
            {
              "number": "7)",
              "text": "35−1:11;"
            },
            {
              "number": "8)",
              "text": "\\(\\frac{46}{9}\\)"
            },
            {
              "number": "9)",
              "text": "3(32+26)+7"
            },
            {
              "number": "10)",
              "text": "\\(\\frac{57}{5}\\)"
            }
          ]
        }
      ]
    },
    {
      "title": "2.22. თითოეული წილადი შეამცირეთ სამჯერ:",
      "blocks": [
        {
          "type": "ordered-list",
          "items": [
            {
              "number": "1)",
              "text": "\\(\\frac{1}{4}\\)"
            },
            {
              "number": "2)",
              "text": "\\(\\frac{8}{11}\\)"
            },
            {
              "number": "3)",
              "text": "\\(\\frac{6}{25}\\)"
            },
            {
              "number": "4)",
              "text": "\\(\\frac{21}{3}\\)"
            }
          ]
        }
      ]
    },
    {
      "title": "2.23.",
      "blocks": [
        {
          "type": "ordered-list",
          "items": [
            {
              "number": "1)",
              "text": "იპოვეთ 4-სა და 0{,}16-ის შებრუნებულების ნამრავლი;"
            },
            {
              "number": "2)",
              "text": "რამდენჯერაა მეტი 0{,}001-ის შებრუნებული 0{,}001-ზე?"
            },
            {
              "number": "3)",
              "text": "იპოვეთ 8-ისა და 7-ის სხვაობის შებრუნებული;"
            },
            {
              "number": "4)",
              "text": "რამდენჯერაა მეტი 1-ისა და $\\frac{4}{15}$-ის ნამრავლის შებრუნებული, მათი შებრუნებულების ნამრავლზე?"
            }
          ]
        }
      ]
    },
    {
      "title": "2.24. მოცემული წილადი ჩაწერეთ სასრული ათწილადის სახით:",
      "blocks": [
        {
          "type": "ordered-list",
          "items": [
            {
              "number": "1)",
              "text": "\\(\\frac{3}{5}\\)"
            },
            {
              "number": "2)",
              "text": "\\(-\\frac{9}{4}\\)"
            },
            {
              "number": "3)",
              "text": "\\(\\frac{7}{8}\\)"
            },
            {
              "number": "4)",
              "text": "\\(\\frac{1}{20}\\)"
            },
            {
              "number": "5)",
              "text": "\\(\\frac{23}{50}\\)"
            },
            {
              "number": "6)",
              "text": "\\(\\frac{35}{16}\\)"
            }
          ]
        }
      ]
    },
    {
      "title": "2.25. მოცემული ათწილადი ჩაწერეთ წილადის სახით:",
      "blocks": [
        {
          "type": "ordered-list",
          "items": [
            {
              "number": "1)",
              "text": "2,25;"
            },
            {
              "number": "2)",
              "text": "3,75;"
            },
            {
              "number": "3)",
              "text": "-11,2;"
            },
            {
              "number": "4)",
              "text": "3,71;"
            },
            {
              "number": "5)",
              "text": "2,05;"
            },
            {
              "number": "6)",
              "text": "-3,001."
            }
          ]
        }
      ]
    },
    {
      "title": "2.26. შეასრულეთ მოქმედებები",
      "blocks": [
        {
          "type": "ordered-list",
          "items": [
            {
              "number": "1)",
              "text": "(2-3,2-5)-10;"
            },
            {
              "number": "2)",
              "text": "(387:100−0,87):2;"
            },
            {
              "number": "3)",
              "text": "1,86−100+15−100:2;"
            },
            {
              "number": "4)",
              "text": "(0,8⋅7+0,64)−(1,25−7−0,8−1,25)."
            }
          ]
        }
      ]
    },
    {
      "title": "2.27. გამოთვალეთ რაციონალური გზით",
      "blocks": [
        {
          "type": "ordered-list",
          "items": [
            {
              "number": "1)",
              "text": "7,27−8,12+9,73−1,88−1,5;"
            },
            {
              "number": "2)",
              "text": "19,9−18−19,9−16+30,1−18−30,1−16;"
            },
            {
              "number": "3)",
              "text": "-1,06+0,04-7,04+2,06;"
            },
            {
              "number": "4)",
              "text": "17,96−0,1−0,1−81,96;"
            },
            {
              "number": "5)",
              "text": "\\(\\frac{1}{23} + \\frac{2}{1} + \\frac{1}{1}\\)"
            },
            {
              "number": "6)",
              "text": "32−23−5⋅7."
            }
          ]
        }
      ]
    },
    {
      "title": "2.28. გამოთვალეთ",
      "blocks": [
        {
          "type": "ordered-list",
          "items": [
            {
              "number": "1)",
              "text": "(26,6−9,7):0,1−180:(10,3−8,5);"
            },
            {
              "number": "2)",
              "text": "(0,63:0,003−5,29:0,023):2,5;"
            },
            {
              "number": "3)",
              "text": "\\((162,162 : 2,25 + 0,828): 0,0125\\)"
            },
            {
              "number": "4)",
              "text": "\\(0,144 + 4,5-2,7 + 1,18+2,18\\)"
            },
            {
              "number": "5)",
              "text": "\\(75,25 +5,75\\)"
            },
            {
              "number": "6)",
              "text": "\\(1-0,88 + 14,6+15,4 + 0,25-40\\)"
            }
          ]
        }
      ]
    },
    {
      "title": "2.29. ჩაწერეთ რაციონალური რიცხვი პერიოდული ათწილადის სახით:",
      "blocks": [
        {
          "type": "ordered-list",
          "items": [
            {
              "number": "1)",
              "text": "\\(\\frac{2}{9}\\)"
            },
            {
              "number": "2)",
              "text": "\\(-\\frac{21}{3}\\)"
            },
            {
              "number": "3)",
              "text": "-13;"
            },
            {
              "number": "4)",
              "text": "\\(\\frac{25}{6}\\)"
            },
            {
              "number": "5)",
              "text": "\\(\\frac{5}{14}\\)"
            },
            {
              "number": "6)",
              "text": "\\(\\frac{5}{12}\\)"
            }
          ]
        }
      ]
    },
    {
      "title": "2.30.",
      "blocks": [
        {
          "type": "ordered-list",
          "items": [
            {
              "number": "1)",
              "text": "ანას მობილური ტელეფონის ანგარიშზე ჰქონდა 10 ლარი და 30 თეთრი. სოფოსთან საუბრის შემდეგ დარჩა 9 ლარი და 60 თეთრი. რამდენ წუთს გრძელდებოდა საუბარი, თუ ერთი წუთის საუბრის ღირებულებაა 0,28 ლარი?"
            },
            {
              "number": "2)",
              "text": "ტაქსისტმა ერთ თვეში 7000 კმ გაიარა. ერთი ლიტრი ბენზინის ღირებულება 2,1 ლარია. ბენზინის საშუალო დანახარჯი ყოველ 100 კმ-ზე 8 ლიტრია. რამდენი ლარი დახარჯა ტაქსისტმა ბენზინზე ერთ თვის განმავლობაში?"
            }
          ]
        }
      ]
    },
    {
      "title": "2.31.",
      "blocks": [
        {
          "type": "ordered-list",
          "items": [
            {
              "number": "1)",
              "text": "სასადილოში 146 კგ ბოსტნეული მიიტანეს: 6 ყუთი პომიდორი და 8 ყუთი კიტრი. რამდენი კგ კიტრი იყო ერთ ყუთში, თუ ყოველ ყუთში იყო 7,8 კგ პომიდორი?"
            },
            {
              "number": "2)",
              "text": "მანქანაზე 163 კგ ხილი დატვირთეს. მსხალი იყო 7 ყუთი, თითოეულ ყუთში 9,4 კგ. რამდენი ყუთი ვაშლი დაუტვირთავთ მანქანაზე, თუ თითო ყუთში იყო 10,8 კგ ხილი?"
            }
          ]
        }
      ]
    },
    {
      "title": "2.32.",
      "blocks": [
        {
          "type": "paragraph",
          "text": "რისი ტოლია -12,7-სა და 10,5-ს შორის მოთავსებული ყველა მთელი რიცხვის ჯამი?"
        }
      ]
    },
    {
      "title": "საკონტროლო ტესტი N 2 (ა)",
      "blocks": [
        {
          "type": "ordered-list",
          "items": [
            {
              "number": "1)",
              "text": "$0{,}5+\\dfrac{1}{3}=$ \\begin{enumerate}[label=ა)]"
            },
            {
              "number": "2)",
              "text": "$\\dfrac{1}{6}$ \\hspace{1.5em}"
            },
            {
              "number": "3)",
              "text": "$\\dfrac{5}{6}$ \\hspace{1.5em}"
            },
            {
              "number": "4)",
              "text": "$\\dfrac{1}{4}$ \\hspace{1.5em}"
            },
            {
              "number": "5)",
              "text": "$\\dfrac{2}{3}$"
            }
          ]
        },
        {
          "type": "paragraph",
          "text": "\\vspace {1em}"
        },
        {
          "type": "paragraph",
          "text": "$\\dfrac {3}{7} \\cdot \\dfrac {7}{3}=$"
        },
        {
          "type": "ordered-list",
          "items": [
            {
              "number": "1)",
              "text": "$19$ \\hspace{1.5em}"
            },
            {
              "number": "2)",
              "text": "$2$ \\hspace{2.5em}"
            },
            {
              "number": "3)",
              "text": "$10$ \\hspace{1.5em}"
            },
            {
              "number": "4)",
              "text": "$2$"
            }
          ]
        },
        {
          "type": "paragraph",
          "text": "\\vspace {1em}"
        },
        {
          "type": "paragraph",
          "text": "$\\left (3\\dfrac {1}{3}\\right )^2=$"
        },
        {
          "type": "ordered-list",
          "items": [
            {
              "number": "1)",
              "text": "$9\\dfrac{1}{9}$ \\hspace{1.5em}"
            },
            {
              "number": "2)",
              "text": "$6\\dfrac{1}{9}$ \\hspace{1.5em}"
            },
            {
              "number": "3)",
              "text": "$10\\dfrac{1}{9}$ \\hspace{1.5em}"
            },
            {
              "number": "4)",
              "text": "$11\\dfrac{1}{9}$"
            }
          ]
        },
        {
          "type": "paragraph",
          "text": "\\vspace {1em}"
        },
        {
          "type": "paragraph",
          "text": "$\\dfrac {0{,}09-0{,}02}{0{,}003} =$"
        },
        {
          "type": "ordered-list",
          "items": [
            {
              "number": "1)",
              "text": "$0,6$ \\hspace{2em}"
            },
            {
              "number": "2)",
              "text": "$0,06$ \\hspace{2em}"
            },
            {
              "number": "3)",
              "text": "$0,006$ \\hspace{2em}"
            },
            {
              "number": "4)",
              "text": "$6$"
            }
          ]
        },
        {
          "type": "paragraph",
          "text": "\\vspace {1em}"
        },
        {
          "type": "paragraph",
          "text": "$\\dfrac {0{,}04 \\cdot 0{,}28}{0{,}4 \\cdot 0{,}7} =$"
        },
        {
          "type": "ordered-list",
          "items": [
            {
              "number": "1)",
              "text": "$0,04$ \\hspace{2em}"
            },
            {
              "number": "2)",
              "text": "$0,004$ \\hspace{2em}"
            },
            {
              "number": "3)",
              "text": "$0,7$ \\hspace{2em}"
            },
            {
              "number": "4)",
              "text": "$0,4$"
            }
          ]
        },
        {
          "type": "paragraph",
          "text": "\\vspace {1em}"
        },
        {
          "type": "paragraph",
          "text": "$\\dfrac {\\dfrac {1}{5}-\\dfrac {4}{5}}{4-1} =$"
        },
        {
          "type": "ordered-list",
          "items": [
            {
              "number": "1)",
              "text": "$\\dfrac{4}{5}$ \\hspace{2em}"
            },
            {
              "number": "2)",
              "text": "$1$ \\hspace{2em}"
            },
            {
              "number": "3)",
              "text": "$\\dfrac{5}{4}$ \\hspace{2em}"
            },
            {
              "number": "4)",
              "text": "$\\dfrac{1}{20}$"
            }
          ]
        },
        {
          "type": "paragraph",
          "text": "\\end {enumerate}"
        },
        {
          "type": "ordered-list",
          "items": [
            {
              "number": "1)",
              "text": "რამდენი მთელი რიცხვია $-3\\frac{1}{10}$-სა და $2\\frac{5}{7}$-ს შორის? ა) 6 \\quad ბ) 5 \\quad გ) 4 \\quad დ) 8"
            },
            {
              "number": "2)",
              "text": "იპოვეთ $a$-ს შებრუნებული რიცხვი, თუ $a=3\\cdot (1\\frac{1}{3} - \\frac{1}{2})$ ა) $\\frac{5}{2}$ \\quad ბ) $\\frac{2}{5}$ \\quad გ) $-\\frac{5}{2}$ \\quad დ) $-\\frac{2}{5}$"
            },
            {
              "number": "3)",
              "text": "იპოვეთ $b$-ს მოპირდაპირე რიცხვი, თუ $b=5\\cdot (1\\frac{1}{3} - \\frac{1}{2})$ ა) $\\frac{5}{6}$ \\quad ბ) $-\\frac{5}{6}$ \\quad გ) $\\frac{6}{5}$ \\quad დ) $-\\frac{6}{5}$"
            },
            {
              "number": "4)",
              "text": "გამოთვალეთ $\\frac{a+1}{a-1}$, თუ $a=\\frac{2}{3}$ ა) $-3$ \\quad ბ) $3$ \\quad გ) $5$ \\quad დ) $-5$"
            },
            {
              "number": "5)",
              "text": "$\\frac{0,15 \\cdot 60}{4,5}=$ ა) 20 \\quad ბ) 200 \\quad გ) 2 \\quad დ) 1,25"
            },
            {
              "number": "6)",
              "text": "მიუთითეთ ყველაზე დიდი რიცხვი ა) 0,00132 \\quad ბ) 0,01799 \\quad გ) 0,12505 \\quad დ) 0,12601"
            },
            {
              "number": "7)",
              "text": "$\\frac{421}{27}$ წილადის მთელი ნაწილი რამდენითაა მეტი $\\frac{273}{27}$ წილადის მთელ ნაწილზე? ა) 2-ით \\quad ბ) 3-ით \\quad გ) 4-ით \\quad დ) 5-ით"
            },
            {
              "number": "8)",
              "text": "მიუთითეთ უმცირესი წილადი ა) $\\frac{15}{40}$ \\quad ბ) $\\frac{225}{300}$ \\quad გ) $\\frac{48}{64}$ \\quad დ) $\\frac{5}{45}$"
            },
            {
              "number": "9)",
              "text": "იპოვეთ ყველა მთელი რიცხვის ჯამი, რომელიც მოთავსებულია $-7,5$-სა და $5,2$-ს შორის ა) $-13$ \\quad ბ) $-12$ \\quad გ) $-11$ \\quad დ) $-10$"
            },
            {
              "number": "10)",
              "text": "ქვემოთ ჩამოთვლილაგან რომელი წილადია $\\frac{1}{6}$-ზე მეტი და $\\frac{2}{5}$-ზე ნაკლები? ა) $\\frac{2}{3}$ \\quad ბ) $\\frac{1}{7}$ \\quad გ) $\\frac{1}{5}$ \\quad დ) $\\frac{1}{2}$"
            }
          ]
        },
        {
          "type": "ordered-list",
          "items": [
            {
              "number": "1)",
              "text": "დადექით $a = \\frac{7}{20};\\ b = \\frac{11}{21};\\ c = \\frac{11}{30}$ ჩაწერეთ ზრდადობის მიხედვით [0.2em] ა) $a,\\ c,\\ b$ \\quad ბ) $a,\\ b,\\ c$ \\quad გ) $c,\\ b,\\ a$ \\quad დ) $b,\\ c,\\ a$"
            },
            {
              "number": "2)",
              "text": "შედარეთ $A_1 = \\frac{1}{2}+\\frac{2}{3}+\\frac{3}{4}$ და $A_2 = \\frac{1}{3}+\\frac{4}{5}+\\frac{5}{6}$ [0.2em] ა) $A_1 > A_2$ \\quad ბ) $A_1 < A_2$ \\quad გ) $A_1 = A_2$ \\quad დ) შედარება შეუძლებელია"
            },
            {
              "number": "3)",
              "text": "$AB$ მოღრძო. $BC$ მოღრძოზე $\\frac{2}{3}\\cdot\\frac{3}{10}$-ით მეტია. $BC$ მოღრძოს სიგრძე $7\\frac{3}{5}$. რამდენი ზომაა $AB$ მოღრძომ $BC$ მოღრძოზე? [0.2em] ა) $\\frac{76}{53}$-ჯერ \\quad ბ) 2-ჯერ \\quad გ) $1\\frac{1}{2}$-ჯერ \\quad დ) შედარება შეუძლებელია"
            },
            {
              "number": "4)",
              "text": "$A,\\ B$ და $C$ წრფეზე რომელი წერტილებია მიჩილდუებული. $B$ წერტილი $A$ და $C$ წერტილებს შორისაა. $AB$ მოღრძოს სიგრძე $2\\frac{3}{5}$ მხარით მეტია $BC$ მოღრძოს სიგრძეზე. რამდენი ზომაა $AC$ მოღრძომ სიგრძე $BC$ მოღრძოს სიგრძეზე? [0.2em] ა) $1\\frac{3}{5}$-ჯერ \\quad ბ) 2-ჯერ \\quad გ) $\\frac{5}{3}$-ჯერ \\quad დ) შედარება შეუძლებელია"
            }
          ]
        }
      ]
    },
    {
      "title": "ბ",
      "blocks": [
        {
          "type": "paragraph",
          "text": "\\textbf {2.33.} რამდენი წილადი მოცემულია $\\frac {2}{3}$-სა და $\\frac {7}{8}$-ს შორის ისეთის, რომელთა მნიშვნებელი 24-ის ტოლია? \\\\"
        },
        {
          "type": "paragraph",
          "text": "დაწერეთ ეს წილადი."
        },
        {
          "type": "paragraph",
          "text": "\\textbf {2.34.} მოიპოვეთ წილადი, რომელიც:\\\\"
        },
        {
          "type": "paragraph",
          "text": "1) მდერია $\\frac {4}{15}$-ზე და ნაკლებია $\\frac {3}{5}$-ზე;\\\\"
        },
        {
          "type": "paragraph",
          "text": "2) უფრო მეტი $\\frac {5}{7}$-ზე და ნაკლებია $\\frac {6}{7}$-ზე."
        },
        {
          "type": "paragraph",
          "text": "\\textbf {2.35.} იპოვეთ ყველა ისეთი ნატურალური რიცხვი $x$, რომლისთვისაც $\\frac {x}{7}$ წილადი არაწყვეტადია და წილადის მნიშვნელობა ნაკლებია 2-ზე."
        },
        {
          "type": "paragraph",
          "text": "\\textbf {2.36.} იპოვეთ ყველა ისეთი ნატურალური რიცხვი $x$, რომლისთვისაც $\\frac {x}{11}$ წილადი რიცხვია და წილადის მნიშვნელობა მეტია $\\frac {1}{2}$-ზე."
        },
        {
          "type": "paragraph",
          "text": "\\textbf {2.37.} იპოვეთ ყველა ისეთი ნატურალური რიცხვი $x$, რომლისთვისაც $\\frac {x}{13}$ წილადი არაწყვეტადია და წილადის მნიშვნელობა ნაკლებია 1,5-ზე."
        }
      ]
    },
    {
      "title": "",
      "blocks": [
        {
          "type": "paragraph",
          "text": "\\textbf {2.38.} რას უდრის იმ $x$ ნატურალური რიცხვების ჯამი, რომელთათვისაც წილადი წესიერია, ხოლო წილადი არაწესიერი?"
        },
        {
          "type": "paragraph",
          "text": "\\textbf {2.39.} შეასრულეთ მოქმედებები"
        },
        {
          "type": "ordered-list",
          "items": [
            {
              "number": "1)",
              "text": "$\\dfrac{x}{11} + \\dfrac{x}{8}$"
            },
            {
              "number": "2)",
              "text": "$1 - 0,64$"
            },
            {
              "number": "3)",
              "text": "$+0,25 - 3,2 + 2 : 10$"
            },
            {
              "number": "4)",
              "text": "$(4,25 : 25) + \\dfrac{7}{7} - \\dfrac{3}{7}$"
            },
            {
              "number": "5)",
              "text": "$(6-3)(0,562+0,138)$"
            },
            {
              "number": "6)",
              "text": "$2-3$"
            }
          ]
        },
        {
          "type": "paragraph",
          "text": "\\textbf {2.40.} შეასრულეთ მოქმედებები"
        },
        {
          "type": "ordered-list",
          "items": [
            {
              "number": "1)",
              "text": "$3\\dfrac{1}{7} - 1\\dfrac{5}{6} + 8 \\cdot 3$"
            },
            {
              "number": "2)",
              "text": "$6 + 8 \\cdot 3$"
            },
            {
              "number": "3)",
              "text": "$6 - 1 - 6 - 20 - 12 + 8$"
            },
            {
              "number": "4)",
              "text": "$0,5 : 0,125 + 2$"
            },
            {
              "number": "5)",
              "text": "$9 - 2 - 1 : 11$"
            }
          ]
        },
        {
          "type": "paragraph",
          "text": "\\textbf {2.41.} შეასრულეთ მოქმედებები"
        },
        {
          "type": "ordered-list",
          "items": [
            {
              "number": "1)",
              "text": "$(0,012 + 0,04104) \\cdot 4560 - 42$"
            },
            {
              "number": "2)",
              "text": "$\\dfrac{4}{8}$"
            },
            {
              "number": "3)",
              "text": "$31,9 + 19,5 : 4$"
            },
            {
              "number": "4)",
              "text": "$62 - 0,16 \\cdot 75$"
            }
          ]
        },
        {
          "type": "paragraph",
          "text": "\\textbf {2.42.} იპოვეთ გამოსახულების მნიშვნელობა"
        },
        {
          "type": "ordered-list",
          "items": [
            {
              "number": "1)",
              "text": "$\\dfrac{1}{2} : 2 + 52 \\cdot 6$"
            },
            {
              "number": "2)",
              "text": "$12 - 8 - 2$"
            },
            {
              "number": "3)",
              "text": "$6 - \\dfrac{4}{3} \\dfrac{17}{13}$"
            },
            {
              "number": "4)",
              "text": "$0,8 : 1,25 - \\dfrac{1}{5}$"
            },
            {
              "number": "5)",
              "text": "$24 + 0,6 + \\dfrac{4}{15}$"
            },
            {
              "number": "6)",
              "text": "$(-1+1):0,5 + 11 - \\dfrac{1}{12} - \\dfrac{1}{60}$"
            },
            {
              "number": "7)",
              "text": "$2,4 - 1,3 - 1,88$"
            },
            {
              "number": "8)",
              "text": "$3 : (0,2-0,1)$"
            },
            {
              "number": "9)",
              "text": "$2,5 - (0,8 + 1,2)$"
            }
          ]
        },
        {
          "type": "paragraph",
          "text": "\\textbf {2.43.} იპოვეთ გამოსახულების მნიშვნელობა $11(1-2-3-4-24)$"
        },
        {
          "type": "paragraph",
          "text": "\\textbf {2.44.} იპოვეთ გამოსახულების მნიშვნელობა"
        },
        {
          "type": "ordered-list",
          "items": [
            {
              "number": "1)",
              "text": "$1 - \\dfrac{1}{10} - \\dfrac{1}{11} - \\dfrac{1}{98} - \\dfrac{1}{99}$"
            }
          ]
        },
        {
          "type": "paragraph",
          "text": "\\textbf {2.45.} გამოთვალეთ"
        },
        {
          "type": "ordered-list",
          "items": [
            {
              "number": "1)",
              "text": "$\\dfrac{730}{15} - \\dfrac{103}{9}$"
            },
            {
              "number": "2)",
              "text": "$432 : (+1) - (2 : 2)$"
            },
            {
              "number": "3)",
              "text": "$2 : 30 + (3+2) : 5$"
            },
            {
              "number": "4)",
              "text": "$6 + 35 \\cdot 1 - 36 : 4$"
            },
            {
              "number": "5)",
              "text": "$2,7 : 0,3 + (-4,5 : 9)$"
            },
            {
              "number": "6)",
              "text": "$1 + 0,125 - \\dfrac{1}{15} + \\dfrac{4}{15}$"
            },
            {
              "number": "7)",
              "text": "$2 - \\dfrac{2}{111} - \\dfrac{2}{113} - \\dfrac{97}{99} - \\dfrac{136}{3}$"
            },
            {
              "number": "8)",
              "text": "$5,25 : (3 + 4,375) : 19$"
            },
            {
              "number": "9)",
              "text": "$1: 2,7 + 2,7 : 1,35 + 0,4 : 2$"
            },
            {
              "number": "10)",
              "text": "$3 : -0,09 : 0,15 : 2 : 5 : 2$"
            },
            {
              "number": "11)",
              "text": "$0,32 - 6 + 0,03 - (5,3 - 3,88) + 0,67 : -4,2 - 13$"
            },
            {
              "number": "12)",
              "text": "$(0,8 - 7 + 0,64) \\cdot 1,25 - 7 - 1,25 + 31,64$"
            },
            {
              "number": "13)",
              "text": "$0,216 : \\dfrac{2}{4} : 0,15 : \\dfrac{3}{15}$"
            },
            {
              "number": "14)",
              "text": "$1,7 : 40 \\cdot 4 : 5$"
            },
            {
              "number": "15)",
              "text": "$196 : 7,7 + 0,695 : 1,39$"
            },
            {
              "number": "16)",
              "text": "$4,5 - 1 + 3,75 : (4,5 \\cdot 1) : \\dfrac{3}{225} : \\dfrac{243}{7} : \\dfrac{135}{1}$"
            },
            {
              "number": "17)",
              "text": "$5 + 0,5 : (3 - 12)$"
            },
            {
              "number": "18)",
              "text": "$2 : 9 : 1,75 : 1,75 - 1 - 17 : 3 : 7 : 1 : 5,1 : \\dfrac{8}{12}$"
            },
            {
              "number": "19)",
              "text": "$(1 - 0,0325) : 400 : 80 - 1 : (6,79 : 0,7 + 0,3)$"
            },
            {
              "number": "20)",
              "text": "$4,5 : 47,375 - 26 - 18 - 0,75 - 2,4 : 0,88 : 3$"
            },
            {
              "number": "21)",
              "text": "$17,81 : 1,37 - 23 : 1$"
            }
          ]
        },
        {
          "type": "paragraph",
          "text": "\\textbf {2.46.} შემდეგი რიცხვის ათწილადის სახით ჩანაწერში იპოვეთ მძიმის შემდეგ 187–ე ციფრი:"
        },
        {
          "type": "ordered-list",
          "items": [
            {
              "number": "1)",
              "text": "$\\dfrac{1}{3}$"
            },
            {
              "number": "2)",
              "text": "$\\dfrac{2}{7}$"
            },
            {
              "number": "3)",
              "text": "$\\dfrac{7}{12}$"
            },
            {
              "number": "4)",
              "text": "$\\dfrac{22}{7}$"
            }
          ]
        },
        {
          "type": "paragraph",
          "text": "\\textbf {2.47.} პერიოდული ათწილადი ჩაწერეთ ჩვეულებრივი წილადის სახით:"
        },
        {
          "type": "ordered-list",
          "items": [
            {
              "number": "1)",
              "text": "$0,(3)$"
            },
            {
              "number": "2)",
              "text": "$0,1(3)$"
            },
            {
              "number": "3)",
              "text": "$0,(23)$"
            },
            {
              "number": "4)",
              "text": "$1,1(6)$"
            },
            {
              "number": "5)",
              "text": "$3,1(45)$"
            },
            {
              "number": "6)",
              "text": "$-1,(2)$"
            }
          ]
        },
        {
          "type": "paragraph",
          "text": "\\textbf {2.48.} გამოთვალეთ: $\\dfrac {11}{50} + \\dfrac {1}{53} - \\dfrac {1}{49}$"
        },
        {
          "type": "paragraph",
          "text": "\\textbf {2.49.} დაამრგვალეთ:"
        },
        {
          "type": "ordered-list",
          "items": [
            {
              "number": "1)",
              "text": "ათეულებამდე – 562, 12674, 300896;"
            },
            {
              "number": "2)",
              "text": "ასეულებამდე – 572, 3751, 472045;"
            },
            {
              "number": "3)",
              "text": "ათასეულებამდე – 1201, 23495, 497003;"
            },
            {
              "number": "4)",
              "text": "მილიონებამდე – 6058364, 270181723, 9624514;"
            },
            {
              "number": "5)",
              "text": "მეასედებამდე – 14,0005, 0,078, 7,926."
            }
          ]
        },
        {
          "type": "paragraph",
          "text": "\\textbf {2.50.} დაამრგვალეთ უმაღლეს თანრიგამდე: \\\\"
        },
        {
          "type": "paragraph",
          "text": "1) 562; \\quad 2) 12005; \\quad 3) 70275; \\quad 4) 980479."
        },
        {
          "type": "paragraph",
          "text": "\\textbf {2.51.} წილადი გადააქციეთ მეასედებამდე დამრგვალებულ ათწილადად: \\\\"
        },
        {
          "type": "paragraph",
          "text": "1) $\\frac {1}{3}$ \\quad 2) $\\frac {4}{9}$ \\quad 3) $\\frac {4}{7}$ \\quad 4) $\\frac {8}{13}$"
        },
        {
          "type": "paragraph",
          "text": "\\textbf {2.52.} ხორბლის მოსავლიანობა ისეთია, რომ $\\frac {2}{5}$ ჰექტრიდან აიღეს $1 \\frac {1}{5}$ ტონა ხორბალი. \\\\"
        },
        {
          "type": "paragraph",
          "text": "1) რამდენი ტონა ხორბალი აუღიათ 1 ჰექტარიდან? \\\\"
        },
        {
          "type": "paragraph",
          "text": "2) რამდენი ჰექტრიდან აუღიათ 1 ტონა ხორბალი?"
        },
        {
          "type": "paragraph",
          "text": "\\textbf {2.53.} მგზავრმა პირველ საათში გაიარა $3 \\frac {3}{5}$ კმ, რაც $\\frac {13}{20}$ კმ-ით ნაკლებია მეორე საათში გავლილ მანძილზე და $\\frac {17}{20}$ კმ-ით მეტია მესამე საათში გავლილ მანძილზე. რამდენი კმ გაიარა სულ მგზავრმა საათში?"
        },
        {
          "type": "paragraph",
          "text": "\\textbf {2.54.} ტრამვაის მარშრუტის სიგრძე $15 \\frac {3}{4}$ კმ-ია. ამ მარშრუტზე 12 გაჩერებაა, თითოეულზე ტრამვაი საშუალოდ $1 \\frac {1}{6}$ წთ დგას. რა დროში გაივლის ტრამვაი მთელ მარშრუტს, თუ მისი სიჩქარეა $26 \\frac {1}{4}$ კმ/სთ?"
        },
        {
          "type": "paragraph",
          "text": "\\textbf {2.55.} ავტობუსი მარშრუტს, რომლის სიგრძე $20 \\frac {1}{4}$ კმ/ია, გადის $\\frac {7}{10}$ სთ-ში. ავტობუსი მოძრაობს 45 კმ/სთ სიჩქარით. რამდენ ხანს გრძელდება საშუალოდ თითო გაჩერება, თუ მარშრუტზე 10 გაჩერებაა?"
        },
        {
          "type": "paragraph",
          "text": "\\textbf {2.56.} სამ სერიან ფილმს 5 სთ-ის განმავლობაში აჩვენებდნენ. პირველ და მეორე სერიას ერთად დასჭირდა $3 \\frac {9}{20}$ სთ, ხოლო მეორე და მესამეს $3 \\frac {1}{12}$ სთ. რა დრო დასჭირდა თითოეულ სერიას?"
        },
        {
          "type": "paragraph",
          "text": "\\textbf {2.57.} ტურისტი მიდიოდა ფეხით $1,5$ სთ-ის განმავლობაში. პირველი ნახევარი საათი მან იარა 5,4 კმ/სთ სიჩქარით, შემდეგი 48 წთ 4,5 კმ/სთ სიჩქარით, დანარჩენი დრო კი 5 კმ/სთ სიჩქარით. რამდენ კილომეტრი გაიარა ტურისტმა სულ?"
        },
        {
          "type": "paragraph",
          "text": "\\textbf {2.58.} ბავშვის პალტოს შესაკერად საჭიროა $1,4$ მ ქსოვილი, ქურთუკისათვის $0,2$ მ–ით ნაკლები. ატელიემ შეკერა 60 პალტო, რომლისთვისაც გამოიყენა მთლიანი ქსოვილის მესამედი. დანარჩენი ქსოვილისაგან შეკერეს ქურთუკები. რამდენი ქურთუკი შეიკერა სულ?"
        },
        {
          "type": "paragraph",
          "text": "\\textbf {2.59.} ფერმერს 6 ძროხა და 4 ცხენი ჰყავს. ერთი ძროხა დღეში საშუალოდ $9 \\frac {1}{4}$ კგ საკვებს ჭამს, ერთი ცხენი კი $13 \\frac {1}{3}$ კგ-ს. რამდენ დღეს ეყოფა ფერმერს $6530$ კგ საკვები ამ ცხოველების გამოსაკვებად?"
        },
        {
          "type": "paragraph",
          "text": "\\textbf {2.60.} მეტალურგიულ საწარმოში 2 ხაზია. პირველი ხაზი 20 ტონა პროდუქციის გამოშვებას 16 საათს ანდომებს, ორივე ხაზი კი 40 ტონა პროდუქციას 12 საათში უშვებს. რა დროს მოანდომებს მარტო მეორე ხაზი 50 ტონა პროდუქციის გამოშვებას?"
        },
        {
          "type": "paragraph",
          "text": "\\textbf {2.61.} ლაი-ლაის აბონენტს ჰქონდა 7 ლარი. რამდენი წუთით მეტს ილაპარაკებს შიდა ქსელში ამ თანხით, თუ გაააქტიურებს შიდა ქსელის 10 თეთრიან ტარიფს, რომელიც 2 ლარი ღირს samson (30 დღეში), ხოლო ჩვეულებრივი წუთის ფასი - 28,8 თეთრია."
        },
        {
          "type": "paragraph",
          "text": "\\noindent"
        },
        {
          "type": "paragraph",
          "text": "\\textbf {2.62.} A-დან ჰაერწერტამდე D ჰაერწერტში სადგი გზით მიდიან. A-დან D-მდე B წერტილზე გავლით გავიდა სადგისის ავტომობილი, რომლის სიგრძე 41 კმ–ია, ხოლო B-დან D-მდე გზა არის 30 კმ, საერთო სიგრძე 71 კმ. C პუნქტიდან გავიდა მეორე ავტომობილი, რომლის სიგრძე არის 28 კმ, ხოლო C-დან D-მდე გზა არის 42 კმ, საერთო სიგრძით 70 კმ. შუაში გზები გადაკვეთს, ხოლო ჰაერწერტამდე A–დან D–მდე, პირდაპირი მანქანის სიგრძე 75 კმ–ია. რამდენჯერ მეტი ავტომობილთა საერთო სიგრძე გავიდა A–დან D–მდე, ვიდრე მოკლე გზით წასულმა მანქანამ? რა დასკვნა შეიძლება გამოიტანოთ?"
        },
        {
          "type": "paragraph",
          "text": "\\vspace {1em}"
        },
        {
          "type": "paragraph",
          "text": "\\begin {center}"
        },
        {
          "type": "paragraph",
          "text": "\\begin {tikzpicture}[scale=1.1]"
        },
        {
          "type": "paragraph",
          "text": "\\tikzset {every node/.style={font=\\sffamily }}"
        },
        {
          "type": "paragraph",
          "text": "% Nodes (positions can be adjusted for a similar look)"
        },
        {
          "type": "paragraph",
          "text": "\\node [circle,draw,fill=black!10,inner sep=2.5pt] (A) at (0,1.5) {A};"
        },
        {
          "type": "paragraph",
          "text": "\\node [circle,draw,fill=black!10,inner sep=2.5pt] (B) at (3,3) {B};"
        },
        {
          "type": "paragraph",
          "text": "\\node [circle,draw,fill=black!10,inner sep=2.5pt] (D) at (4,0) {D};"
        },
        {
          "type": "paragraph",
          "text": "\\node [circle,draw,fill=black!10,inner sep=2.5pt] (C) at (0,-1.5) {C};"
        },
        {
          "type": "paragraph",
          "text": "% Edges with weights"
        },
        {
          "type": "paragraph",
          "text": "\\draw [line width=1pt] (A) -- node[above left=0.1cm, near start] {\\scriptsize 41} (B);"
        },
        {
          "type": "paragraph",
          "text": "\\draw [line width=1pt] (B) -- node[right=0.1cm, midway] {\\scriptsize 30} (D);"
        },
        {
          "type": "paragraph",
          "text": "\\draw [line width=1pt] (A) -- node[right, midway] {\\scriptsize 75} (D);"
        },
        {
          "type": "paragraph",
          "text": "\\draw [line width=1pt] (A) -- node[below left=0.1cm, near start] {\\scriptsize 28} (C);"
        },
        {
          "type": "paragraph",
          "text": "\\draw [line width=1pt] (C) -- node[below=0.05cm, midway] {\\scriptsize 42} (D);"
        },
        {
          "type": "paragraph",
          "text": "% Optional: dots for emphasis"
        },
        {
          "type": "paragraph",
          "text": "%\\fill (A) circle (1.1pt);"
        },
        {
          "type": "paragraph",
          "text": "%\\fill (B) circle (1.1pt);"
        },
        {
          "type": "paragraph",
          "text": "%\\fill (C) circle (1.1pt);"
        },
        {
          "type": "paragraph",
          "text": "%\\fill (D) circle (1.1pt);"
        },
        {
          "type": "paragraph",
          "text": "\\end {tikzpicture}"
        },
        {
          "type": "paragraph",
          "text": "\\end {center}"
        }
      ]
    },
    {
      "title": "საკონტროლო ბლოკი",
      "type": "quiz",
      "quiz": {
        "questions": [
          {
            "id": "p2q1",
            "number": "1.",
            "prompt": "რომელი წილადი უფრო მეტია?",
            "options": [
              {
                "value": "a",
                "label": "$\\tfrac{4}{11}$"
              },
              {
                "value": "b",
                "label": "$\\tfrac{6}{11}$"
              }
            ]
          },
          {
            "id": "p2q2",
            "number": "2.",
            "prompt": "10 პაკეტად განაწილებული 2 კგ შოკოლადი და 15 პაკეტად განაწილებული 5 კგ ნამცხვარი — რომელ პაკეტშია მეტი მასა?",
            "options": [
              {
                "value": "a",
                "label": "შოკოლადის პაკეტში"
              },
              {
                "value": "b",
                "label": "ნამცხვრის პაკეტში"
              }
            ]
          },
          {
            "id": "p2q3",
            "number": "3.",
            "prompt": "რომელი ტურისტი დადის უფრო სწრაფად?",
            "options": [
              {
                "value": "a",
                "label": "პირველი ტურისტი (21 კმ / 2 სთ)"
              },
              {
                "value": "b",
                "label": "მეორე ტურისტი (28 კმ / 3 სთ)"
              }
            ]
          },
          {
            "id": "p2q4",
            "number": "4.",
            "prompt": "რომელი წილადი უფრო ახლოსაა ერთიანთან?",
            "options": [
              {
                "value": "a",
                "label": "$\\tfrac{7}{8}$"
              },
              {
                "value": "b",
                "label": "$\\tfrac{99}{100}$"
              }
            ]
          },
          {
            "id": "p2q5",
            "number": "5.",
            "prompt": "რომელია $\\tfrac{11}{8}$-ის შერეული წილადის ჩანაწერი?",
            "options": [
              {
                "value": "a",
                "label": "$1\\tfrac{3}{8}$"
              },
              {
                "value": "b",
                "label": "$1\\tfrac{4}{8}$"
              },
              {
                "value": "c",
                "label": "$2\\tfrac{3}{8}$"
              }
            ]
          }
        ],
        "answerKey": {
          "p2q1": {
            "correct": "b",
            "explanation": "$\\tfrac{6}{11}$-ს უფრო დიდი მრიცხველი აქვს საერთო მაკრიზთან 11.",
            "scored": true
          },
          "p2q2": {
            "correct": "b",
            "explanation": "ნამცხვრის თითო პაკეტი იწონის $5/15=1/3$ კგ-ს, რაც მეტია ვიდრე $2/10=0.2$ კგ.",
            "scored": true
          },
          "p2q3": {
            "correct": "a",
            "explanation": "პირველი ტურისტის სიჩქარეა $21/2=10.5$ კმ/სთ, მეორე ტურისტის — $28/3≈9.33$ კმ/სთ.",
            "scored": true
          },
          "p2q4": {
            "correct": "b",
            "explanation": "$\\tfrac{99}{100}$ ერთიანიდან მხოლოდ $0.01$-ით განსხვავდება.",
            "scored": true
          },
          "p2q5": {
            "correct": "a",
            "explanation": "$\\tfrac{11}{8}=1\\tfrac{3}{8}$ შერეული წილადის სახით.",
            "scored": true
          }
        }
      }
    }
  ]
}